[
  {
    "symbol": "USD",
    "name": "US Dollar",
    "amount": 6738.106038793008,
    "averagePrice": 1,
    "transactions": [
      {
        "type": "buy",
        "symbol": "BTC",
        "amount": 0.05,
        "price": 65237.87922413983,
        "timestamp": "2025-04-29T01:02:39.850Z"
      }
    ]
  },
  {
    "symbol": "BTC",
    "name": "BTC",
    "amount": 0.05,
    "averagePrice": 65237.87922413983,
    "transactions": [
      {
        "type": "buy",
        "symbol": "BTC",
        "amount": 0.05,
        "price": 65237.87922413983,
        "timestamp": "2025-04-29T01:02:39.850Z"
      }
    ]
  }
]